ntt_file_system_checker/FileContentChecker.py
ntt_file_system_checker/FileContentCheckingService.py
ntt_file_system_checker/IFileContentChecker.py
ntt_file_system_checker/IFileContentCheckingService.py
ntt_file_system_checker/__init__.py
ntt_file_system_checker/constants.py
ntt_file_system_checker-1.0.2.dist-info/LICENSE
ntt_file_system_checker-1.0.2.dist-info/METADATA
ntt_file_system_checker-1.0.2.dist-info/WHEEL
ntt_file_system_checker-1.0.2.dist-info/top_level.txt
ntt_file_system_checker-1.0.2.dist-info/RECORD
